pc_jamf/__init__.py
pc_jamf-0.4.8.dist-info/LICENSE
pc_jamf-0.4.8.dist-info/METADATA
pc_jamf-0.4.8.dist-info/WHEEL
pc_jamf-0.4.8.dist-info/top_level.txt
pc_jamf-0.4.8.dist-info/RECORD
