Metadata-Version: 2.1
Name: pc-jamf
Version: 0.4.8
Summary: Wrapper library to connect to a JAMF Pro Server using the beta and classic API
Home-page: https://github.com/pinecrest/pc_jamf
Author: Sean Tibor
Author-email: sean.tibor@pinecrest.edu
License: GPLv3
Platform: UNKNOWN
Classifier: License :: OSI Approved :: GNU General Public License v3 or later (GPLv3+)
Classifier: Programming Language :: Python :: 3.8
Classifier: Programming Language :: Python :: 3
Classifier: Operating System :: OS Independent
Classifier: Topic :: Software Development :: Libraries :: Python Modules
Classifier: Development Status :: 4 - Beta
Classifier: Intended Audience :: Developers
Classifier: Intended Audience :: Information Technology
Classifier: Intended Audience :: System Administrators
License-File: LICENSE
Requires-Dist: requests
Requires-Dist: python-decouple
